{
	"af": "Seburu",
	"ar": "Se-arab",
	"az": "Se-azerbaijani",
	"be": "Se-belarusia",
	"bg": "Se-bulgaria",
	"bn": "Se-bengali",
	"bs": "Se-bosnia",
	"ca": "Se-catalia",
	"ceb": "Se-cebuano",
	"cs": "Se-czech",
	"cy": "Se-welsh",
	"da": "Se-dutch",
	"de": "Se-jeremane",
	"el": "Segerike",
	"en": "Senyesemane",
	"eo": "Se-esperanto",
	"es": "Sespain",
	"et": "Se-estonia",
	"eu": "Se-basque",
	"fa": "Se-persia",
	"fi": "Se-finnish",
	"fr": "Sefora",
	"ga": "Se-irish",
	"gl": "Se-galicia",
	"gu": "Se-gujarati",
	"ha": "Sehausa",
	"hi": "Se-hindi",
	"hmn": "Se-hmong",
	"hr": "Se-croatia",
	"ht": "Se-Creole sa Haiti",
	"hu": "Se-hungaria",
	"hy": "Se-armenia",
	"id": "Se-indonesia",
	"ig": "Se-igbo",
	"is": "Se-iceland",
	"it": "Se-tariana",
	"iw": "Seheberu",
	"ja": "Se-japane",
	"jw": "Se-javane",
	"ka": "Se-geogia",
	"kk": "Se-kazakh",
	"km": "Se-khmer",
	"kn": "Se-kannada",
	"ko": "Se-korea",
	"la": "Se-latino",
	"lo": "Se-lao",
	"lt": "Se-lithuania",
	"lv": "Se-latvia",
	"mg": "Se-malagasy",
	"mi": "Semaori",
	"mk": "Se-masedonia",
	"ml": "Se-malayalam",
	"mn": "Se-mongolia",
	"mr": "Se-marathi",
	"ms": "Se-malay",
	"mt": "Se-maltese",
	"my": "Se-Burmese",
	"ne": "Se-nepali",
	"no": "Se-norway",
	"ny": "Se-Chichewa",
	"pa": "Se-punjabi",
	"pl": "Se-polish",
	"pt": "Sepotokise",
	"ro": "Se-romania",
	"ru": "Se-russia",
	"si": "Sinhala",
	"sk": "Se-slovak",
	"sl": "Se-slovania",
	"so": "Se-somali",
	"sq": "Se-albanian",
	"sr": "Se-serbian",
	"st": "Sesotho",
	"su": "Se-sundanese",
	"sv": "Se-sweden",
	"sw": "Se-swahili",
	"ta": "Se-tamil",
	"te": "Se-telegu",
	"tg": "Se-tajik",
	"th": "Se-thai",
	"tl": "Sefilipino",
	"tr": "Se-theki",
	"uk": "Se-ukrania",
	"ur": "Se-urdu",
	"uz": "Se-uzbek",
	"vi": "Se-vietnam",
	"yi": "Se-yiddish",
	"yo": "Se-yoruba",
	"zh": "Sechaena (Nolofaditswe)",
	"zh-TW": "Sechaena",
	"zu": "se Zulu"
}